c4m/flexio/__init__.py
c4m/flexio/_helpers.py
c4m/flexio/cell.py
c4m/flexio/factory.py
c4m/flexio/specification.py
c4m_flexio-0.4.9.dist-info/METADATA
c4m_flexio-0.4.9.dist-info/WHEEL
c4m_flexio-0.4.9.dist-info/entry_points.txt
c4m_flexio-0.4.9.dist-info/licenses/LICENSE.md
c4m_flexio-0.4.9.dist-info/RECORD
