Metadata-Version: 2.1
Name: c4m-flexio
Version: 0.4.9
Summary: PDKMaster based scalable IO library
Author: Chips4Makers contributors
License: GPL-2.0-or-later OR AGPL-3.0-or-later OR CERN-OHL-S-2.0+
Requires-Python: ~=3.8
Requires-Dist: PDKMaster~=0.12.0
Requires-Dist: c4m-flexcell~=0.4.6
